LonginusPYPI/LClient.py
LonginusPYPI/LServer.py
LonginusPYPI/LonginusP.py
LonginusPYPI/Lshell.py
LonginusPYPI/__init__.py
LonginusPYPl-0.2.8.dist-info/METADATA
LonginusPYPl-0.2.8.dist-info/WHEEL
LonginusPYPl-0.2.8.dist-info/top_level.txt
LonginusPYPl-0.2.8.dist-info/RECORD
